rst2pdf/__init__.py
rst2pdf/basenodehandler.py
rst2pdf/config.py
rst2pdf/createpdf.py
rst2pdf/dumpstyle.py
rst2pdf/findfonts.py
rst2pdf/flowables.py
rst2pdf/genelements.py
rst2pdf/genpdftext.py
rst2pdf/image.py
rst2pdf/languages.py
rst2pdf/log.py
rst2pdf/math_flowable.py
rst2pdf/nodehandlers.py
rst2pdf/pdfbuilder.py
rst2pdf/pygments2style.py
rst2pdf/roman_numerals.py
rst2pdf/rson.py
rst2pdf/sectnumlinks.py
rst2pdf/sinker.py
rst2pdf/sphinxnodes.py
rst2pdf/style2yaml.py
rst2pdf/styles.py
rst2pdf/svgimage.py
rst2pdf/utils.py
rst2pdf/writer.py
rst2pdf/directives/__init__.py
rst2pdf/directives/aafigure.py
rst2pdf/directives/code_block.py
rst2pdf/directives/contents.py
rst2pdf/directives/noop.py
rst2pdf/directives/oddeven.py
rst2pdf/extensions/__init__.py
rst2pdf/extensions/dotted_toc.py
rst2pdf/extensions/fancytitles.py
rst2pdf/extensions/plantuml_r2p.py
rst2pdf/extensions/preprocess_r2p.py
rst2pdf/extensions/sample.py
rst2pdf/images/image-missing.jpg
rst2pdf/images/image-missing.png
rst2pdf/roles/__init__.py
rst2pdf/roles/counter.py
rst2pdf/roles/counter_off.py
rst2pdf/roles/package.py
rst2pdf/styles/11x17.yaml
rst2pdf/styles/a0.yaml
rst2pdf/styles/a1-landscape.yaml
rst2pdf/styles/a1.yaml
rst2pdf/styles/a2-landscape.yaml
rst2pdf/styles/a2.yaml
rst2pdf/styles/a3-landscape.yaml
rst2pdf/styles/a3.yaml
rst2pdf/styles/a4-landscape.yaml
rst2pdf/styles/a4.yaml
rst2pdf/styles/a5-landscape.yaml
rst2pdf/styles/a5.yaml
rst2pdf/styles/a6-landscape.yaml
rst2pdf/styles/a6.yaml
rst2pdf/styles/abap.yaml
rst2pdf/styles/algol.yaml
rst2pdf/styles/algol_nu.yaml
rst2pdf/styles/arduino.yaml
rst2pdf/styles/autumn.yaml
rst2pdf/styles/b0.yaml
rst2pdf/styles/b1-landscape.yaml
rst2pdf/styles/b1.yaml
rst2pdf/styles/b2-landscape.yaml
rst2pdf/styles/b2.yaml
rst2pdf/styles/b3-landscape.yaml
rst2pdf/styles/b3.yaml
rst2pdf/styles/b4-landscape.yaml
rst2pdf/styles/b4.yaml
rst2pdf/styles/b5-landscape.yaml
rst2pdf/styles/b5.yaml
rst2pdf/styles/b6-landscape.yaml
rst2pdf/styles/b6.yaml
rst2pdf-0.104.dist-info/METADATA
rst2pdf-0.104.dist-info/WHEEL
rst2pdf-0.104.dist-info/entry_points.txt
rst2pdf-0.104.dist-info/top_level.txt
rst2pdf-0.104.dist-info/RECORD
