Metadata-Version: 2.4
Name: rst2pdf
Version: 0.104
Summary: Convert reStructured Text to PDF via ReportLab.
Author-email: rst2pdf maintainers <maintainers@rstpdf.org>
License: Copyright (c) 2007-2020 Roberto Alsina and the contributors to the rst2pdf project
Project-URL: Homepage, https://rst2pdf.org
Project-URL: Changelog, https://github.com/rst2pdf/rst2pdf/blob/master/CHANGES.rst
Project-URL: Releases, https://github.com/rst2pdf/rst2pdf/releases
Project-URL: Source, https://github.com/rst2pdf/rst2pdf
Project-URL: Bug Reports, https://github.com/rst2pdf/rst2pdf/issues
Keywords: convert,docutils,pdf,pygments,reportlab',restructured,rst
Classifier: Development Status :: 4 - Beta
Classifier: Environment :: Console
Classifier: License :: OSI Approved :: MIT License
Classifier: Operating System :: OS Independent
Classifier: Programming Language :: Python :: 3
Classifier: Programming Language :: Python :: 3.10
Classifier: Programming Language :: Python :: 3.11
Classifier: Programming Language :: Python :: 3.12
Classifier: Programming Language :: Python :: 3.13
Classifier: Programming Language :: Python :: 3.14
Classifier: Topic :: Documentation
Classifier: Topic :: Software Development :: Libraries :: Python Modules
Classifier: Topic :: Text Processing
Classifier: Topic :: Utilities
Requires-Python: >=3.10
Requires-Dist: docutils>=0.21.2
Requires-Dist: jinja2~=3.0
Requires-Dist: packaging~=25.0
Requires-Dist: pygments~=2.0
Requires-Dist: pyyaml>=6.0.1
Requires-Dist: reportlab~=4.0
Provides-Extra: aafiguresupport
Requires-Dist: aafigure; extra == "aafiguresupport"
Provides-Extra: mathsupport
Requires-Dist: matplotlib; extra == "mathsupport"
Provides-Extra: plantumlsupport
Requires-Dist: plantuml; extra == "plantumlsupport"
Provides-Extra: rawhtmlsupport
Requires-Dist: xhtml2pdf; extra == "rawhtmlsupport"
Provides-Extra: sphinx
Requires-Dist: sphinx>7.3; python_version == "3.10" and extra == "sphinx"
Requires-Dist: sphinx>=8.2; python_version >= "3.11" and extra == "sphinx"
Provides-Extra: svgsupport
Requires-Dist: svglib; extra == "svgsupport"
